{
    "sourceFile": "SobreNos.html",
    "activeCommit": 0,
    "commits": [
        {
            "activePatchIndex": 2,
            "patches": [
                {
                    "date": 1707868110225,
                    "content": "Index: \n===================================================================\n--- \n+++ \n"
                },
                {
                    "date": 1707868117519,
                    "content": "Index: \n===================================================================\n--- \n+++ \n@@ -65,9 +65,9 @@\n             </div>\r\n             <!-- Background image -->\r\n           </header>\r\n <!--Começo do texto-->\r\n-<h1></h1>\r\n+<h1 class=\"\"></h1>\r\n <!--Fim do texto-->\r\n \r\n \r\n \r\n"
                },
                {
                    "date": 1707868184027,
                    "content": "Index: \n===================================================================\n--- \n+++ \n@@ -65,9 +65,9 @@\n             </div>\r\n             <!-- Background image -->\r\n           </header>\r\n <!--Começo do texto-->\r\n-<h1 class=\"bi-text-right\">Quem somos</h1>\r\n+<h1 class=\"text-right\">Quem somos</h1>\r\n <!--Fim do texto-->\r\n \r\n \r\n \r\n"
                }
            ],
            "date": 1707868110225,
            "name": "Commit-0",
            "content": "<!doctype html>\r\n<html lang=\"en\" data-bs-theme=\"auto\">\r\n  <head><script src=\"../assets/js/color-modes.js\"></script>\r\n\r\n    <meta charset=\"utf-8\">\r\n    <meta name=\"viewport\" content=\"width=device-width, initial-scale=1\">\r\n    <meta name=\"description\" content=\"\">\r\n    <meta name=\"author\" content=\"Mark Otto, Jacob Thornton, and Bootstrap contributors\">\r\n    <meta name=\"generator\" content=\"Hugo 0.118.2\">\r\n    <title>Preços | Rifas Atletas</title>\r\n\r\n    <link rel=\"canonical\" href=\"https://getbootstrap.com/docs/5.3/examples/pricing/\">\r\n    <link href=\"https://cdn.jsdelivr.net/npm/bootstrap@5.3.2/dist/css/bootstrap.min.css\" rel=\"stylesheet\" integrity=\"sha384-T3c6CoIi6uLrA9TneNEoa7RxnatzjcDSCmG1MXxSR1GAsXEV/Dwwykc2MPK8M2HN\" crossorigin=\"anonymous\">\r\n    <link rel=\"stylesheet\" href=\"https://cdn.jsdelivr.net/npm/bootstrap-icons@1.11.3/font/bootstrap-icons.min.css\">\r\n    <link rel=\"stylesheet\" href=\"https://cdn.jsdelivr.net/npm/@docsearch/css@3\">\r\n    <link href=\"../assets/dist/css/bootstrap.min.css\" rel=\"stylesheet\">\r\n    <link  rel=\"shortcut icon\" type=\"imagex/png\" href=\"/img/Logo.ico\">\r\n    <body>\r\n        <header>\r\n          <!--Começo da navbar-->\r\n        <div class=\"container\">\r\n            <header class=\"d-flex flex-wrap align-items-center justify-content-center justify-content-md-between py-3 mb-4\">\r\n              <div class=\"col-md-3 mb-2 mb-md-0\">\r\n                <nav class=\"navbar\">\r\n                  <div class=\"container-fluid\">\r\n                    <a class=\"navbar-brand\" href=\"#\">\r\n                      <img src=\"img/Logo.png\" alt=\"Bootstrap\" width=\"90\" height=\"80\">\r\n                    </a>\r\n                </nav>\r\n              </div>\r\n              <ul class=\"nav col-12 col-md-auto mb-2 justify-content-center\">\r\n                <li><a href=\"Precos.html\" class=\"nav-link text-danger fw-bold\">Preços</a></li>\r\n                <li><a href=\"#\" class=\"nav-link text-danger fw-bold\">Ajuda</a></li>\r\n                <li><a href=\"#\" class=\"nav-link text-danger fw-bold\">Sobre nós</a></li>\r\n              </ul>\r\n              <div class=\"col-md-3 text-end\">\r\n                <a href=\"Login.html\"><button type=\"button\"  class=\"btn text-danger me-2 fw-bold\" href>Login</button></a>\r\n                \r\n                <a href=\"Registro.html\"><button type=\"button\"  class=\"btn btn-danger  fw-bold\" href>Cadastra-se</button></a>\r\n              </div>\r\n            </header>\r\n          </div>\r\n          <!--Fim da navbar-->\r\n\r\n\r\n\r\n            <!-- Background image -->\r\n            <div class=\"p-5  bg-image\" style=\"background-image: url('img/rifa.jpg'); height: 400px;\">\r\n              <div class=\"mask\">\r\n                <div class=\"d-flex justify-content-center align-items-center h-100\">\r\n                    <div class=\"px-4 py-5 my-5 text-center\">\r\n                        <h1 class=\"display-5 fw-bold text-light\">Crie sua Rifa Online de Forma Prática e Rápida</h1>\r\n                        <div class=\"col-lg-6 mx-auto\">\r\n              \r\n                         \r\n                          </div>\r\n                        </div>\r\n                      </div>\r\n                    \r\n                    \r\n                    \r\n                  </div>\r\n                </div>\r\n              </div>\r\n            </div>\r\n            <!-- Background image -->\r\n          </header>\r\n<!--Começo do texto-->\r\n<h\r\n<!--Fim do texto-->\r\n\r\n\r\n\r\n\r\n           <!--Footer-->\r\n\r\n  <!-- Section: Social media -->\r\n  <section class=\"d-flex justify-content-center justify-content-lg-between p-4 \">\r\n   \r\n  </section>\r\n  <!-- Section: Social media -->\r\n\r\n  <!-- Section: Links  -->\r\n  <section class=\"\">\r\n    <div class=\"container text-center text-md-start mt-5 text-light fw-bold\">\r\n      <!-- Grid row -->\r\n      <div class=\"row mt-3\">\r\n        <!-- Grid column -->\r\n        <div class=\"col-md-3 col-lg-4 col-xl-3 mx-auto mb-4\">\r\n          <!-- Content -->\r\n          <h6 class=\"text-uppercase fw-bold mb-4 text-danger\">\r\n            <img src=\"img/Logo.ico\" class=\"w-50\">\r\n          </h6>\r\n          <p class=\"text-danger fw-bold\">\r\n            Plataforma inovadora para apoiar atletas em suas jornadas.\r\n          </p>\r\n        </div>\r\n        <!-- Grid column -->\r\n\r\n        <!-- Grid column -->\r\n        <div class=\"col-md-2 col-lg-2 col-xl-2 mx-auto mb-4\">\r\n          <!-- Links -->\r\n          <h6 class=\"text-uppercase fw-bold mb-4 text-danger-emphasis\">\r\n            Páginas\r\n          </h6>\r\n          <p>\r\n            <a href=\"Index.html\" class=\" text-danger text-decoration-none\">Inicio</a>\r\n          </p>\r\n          <p>\r\n            <a href=\"#!\" class=\" text-danger text-decoration-none\">Preço</a>\r\n          </p>\r\n          <p>\r\n            <a href=\"#!\" class=\" text-danger text-decoration-none\">Sobre nós</a>\r\n          </p>\r\n          <p>\r\n            <a href=\"#!\" class=\" text-danger text-decoration-none \">Termos de uso e Privacidade</a>\r\n          </p>\r\n        </div>\r\n        <!-- Grid column -->\r\n\r\n        <!-- Grid column -->\r\n        <div class=\"col-md-3 col-lg-2 col-xl-2 mx-auto mb-4\">\r\n          <!-- Links -->\r\n          <h6 class=\"text-uppercase fw-bold mb-4 text-danger-emphasis\">\r\n            Ajuda\r\n          </h6>\r\n          <p>\r\n            <a href=\"#!\" class=\"text-danger text-decoration-none\">Central de Ajuda</a>\r\n          </p>\r\n          <p>\r\n            <a href=\"#!\" class=\"text-danger text-decoration-none\">Dúvidas Frequentes</a>\r\n          </p>\r\n      \r\n        \r\n        </div>\r\n        <!-- Grid column -->\r\n\r\n        <!-- Grid column -->\r\n        <div class=\"col-md-4 col-lg-3 col-xl-3 mx-auto mb-md-0 mb-4 text-danger\">\r\n          <!-- Links -->\r\n          <h6 class=\"text-uppercase fw-bold mb-4 text-danger-emphasis\">Contato</h6>\r\n          \r\n      <p class=\"text-danger me-3\">rifamy@gmail.com</p>\r\n          <a href=\"\" class=\"text-decoration-none me-3 text-danger\">Whatsapp</a>\r\n         \r\n        </div>\r\n        <!-- Grid column -->\r\n      </div>\r\n      <!-- Grid row -->\r\n    </div>\r\n  </section>\r\n  <!-- Section: Links  -->\r\n\r\n  <!-- Copyright -->\r\n  <div class=\"text-center p-4 text-light container-fluid\">\r\n    © 2024 Copyright:\r\n    <a class=\"text-reset fw-bold\" href=\"https://mdbootstrap.com/\">MW</a>\r\n  </div>\r\n  <!-- Copyright -->\r\n</footer>\r\n<!-- Footer -->\r\n<!--Fim do footer-->\r\n\r\n    </body>\r\n    <html>"
        }
    ]
}